mlf_core/__init__.py
mlf_core/__main__.py
mlf_core/bump_version/__init__.py
mlf_core/bump_version/bump_version.py
mlf_core/common/__init__.py
mlf_core/common/levensthein_dist.py
mlf_core/common/load_yaml.py
mlf_core/common/suggest_similar_commands.py
mlf_core/common/version.py
mlf_core/config/__init__.py
mlf_core/config/config.py
mlf_core/create/__init__.py
mlf_core/create/create.py
mlf_core/create/domains/__init__.py
mlf_core/create/domains/mlf_core_template_struct.py
mlf_core/create/domains/mlflow_creator.py
mlf_core/create/domains/package_creator.py
mlf_core/create/github_support.py
mlf_core/create/template_creator.py
mlf_core/create/templates/available_templates.yml
mlf_core/create/templates/common_all_files/cookiecutter.json
mlf_core/create/templates/common_all_files/{{cookiecutter.common_all}}/.bandit.yml
mlf_core/create/templates/common_all_files/{{cookiecutter.common_all}}/.editorconfig
mlf_core/create/templates/common_all_files/{{cookiecutter.common_all}}/.gitattributes
mlf_core/create/templates/common_all_files/{{cookiecutter.common_all}}/.github/ISSUE_TEMPLATE/bug_report.md
mlf_core/create/templates/common_all_files/{{cookiecutter.common_all}}/.github/ISSUE_TEMPLATE/feature_request.md
mlf_core/create/templates/common_all_files/{{cookiecutter.common_all}}/.github/ISSUE_TEMPLATE/general_question.md
mlf_core/create/templates/common_all_files/{{cookiecutter.common_all}}/.github/pull_request_template.md
mlf_core/create/templates/common_all_files/{{cookiecutter.common_all}}/.github/workflows/lint.yml
mlf_core/create/templates/common_all_files/{{cookiecutter.common_all}}/.github/workflows/master_main_branch_protection.yml
mlf_core/create/templates/common_all_files/{{cookiecutter.common_all}}/.github/workflows/publish_docs.yml
mlf_core/create/templates/common_all_files/{{cookiecutter.common_all}}/.github/workflows/sync.yml
mlf_core/create/templates/common_all_files/{{cookiecutter.common_all}}/.gitignore
mlf_core-1.11.4.dist-info/entry_points.txt
mlf_core-1.11.4.dist-info/LICENSE
mlf_core-1.11.4.dist-info/WHEEL
mlf_core-1.11.4.dist-info/METADATA
mlf_core-1.11.4.dist-info/RECORD
