Metadata-Version: 2.1
Name: mlf-core
Version: 1.11.4
Summary: Reproducible machine learning pipelines using mlflow.
Home-page: https://github.com/mlf-core/mlf-core
License: Apache2.0
Author: Lukas Heumos
Author-email: lukas.heumos@posteo.net
Requires-Python: >=3.6.1,<3.10
Classifier: License :: Other/Proprietary License
Classifier: Programming Language :: Python :: 3
Classifier: Programming Language :: Python :: 3.7
Classifier: Programming Language :: Python :: 3.8
Classifier: Programming Language :: Python :: 3.9
Requires-Dist: GitPython (>=3.1.15,<4.0.0)
Requires-Dist: Jinja2 (>=2.11.3,<4.0.0)
Requires-Dist: PyGithub (>=1.54.1,<2.0.0)
Requires-Dist: PyNaCl (>=1.4.0,<2.0.0)
Requires-Dist: PyYAML (>=5.4.1,<7.0.0)
Requires-Dist: appdirs (>=1.4.4,<2.0.0)
Requires-Dist: autopep8 (>=1.5.6,<2.0.0)
Requires-Dist: cffi (>=1.14.5,<2.0.0)
Requires-Dist: click (>=7.1.2,<9.0.0)
Requires-Dist: cookiecutter (>=1.7.2,<2.0.0)
Requires-Dist: cryptography (>=3.4.7,<36.0.0)
Requires-Dist: mlflow (>=1.15.0,<2.0.0)
Requires-Dist: packaging (>=20.9,<22.0)
Requires-Dist: questionary (>=1.9.0,<2.0.0)
Requires-Dist: requests (>=2.25.1,<3.0.0)
Requires-Dist: rich (>=10.1.0,<11.0.0)
Requires-Dist: ruamel.yaml (>=0.17.4,<0.18.0)
Project-URL: Documentation, https://mlf-core.readthedocs.io
Project-URL: Repository, https://github.com/mlf-core/mlf-core
